odoo10_addon_web_sheet_full_width-10.0.1.0.1-py2.7-nspkg.pth
odoo10_addon_web_sheet_full_width-10.0.1.0.1.dist-info/top_level.txt
odoo10_addon_web_sheet_full_width-10.0.1.0.1.dist-info/WHEEL
odoo10_addon_web_sheet_full_width-10.0.1.0.1.dist-info/RECORD
odoo10_addon_web_sheet_full_width-10.0.1.0.1.dist-info/metadata.json
odoo10_addon_web_sheet_full_width-10.0.1.0.1.dist-info/DESCRIPTION.rst
odoo10_addon_web_sheet_full_width-10.0.1.0.1.dist-info/METADATA
odoo10_addon_web_sheet_full_width-10.0.1.0.1.dist-info/namespace_packages.txt
odoo/addons/web_sheet_full_width/__manifest__.py
odoo/addons/web_sheet_full_width/__init__.py
odoo/addons/web_sheet_full_width/README.rst
odoo/addons/web_sheet_full_width/view/qweb.xml
odoo/addons/web_sheet_full_width/static/description/icon.png
odoo/addons/web_sheet_full_width/static/src/css/web_sheet_full_width.less
