Metadata-Version: 2.0
Name: odoo10-addon-web-sheet-full-width
Version: 10.0.1.0.1
Summary: Use the whole available screen width when displaying sheets
Home-page: UNKNOWN
Author: Therp BV,Sudokeys,GRAP,Odoo Community Association (OCA)
Author-email: support@odoo-community.org
License: AGPL-3
Platform: UNKNOWN
Requires-Dist: odoo (<10.1dev,>=10.0)
Classifier: Programming Language :: Python :: 2.7
Classifier: Framework :: Odoo
Classifier: License :: OSI Approved :: GNU Affero General Public License v3
